cow_web_ext/__init__.py
cow_web_ext-0.2.1.dist-info/LICENSE
cow_web_ext-0.2.1.dist-info/METADATA
cow_web_ext-0.2.1.dist-info/WHEEL
cow_web_ext-0.2.1.dist-info/entry_points.txt
cow_web_ext-0.2.1.dist-info/top_level.txt
cow_web_ext-0.2.1.dist-info/RECORD
