Metadata-Version: 2.1
Name: cow-web-ext
Version: 0.2.1
Summary: Host application for the Content Override & Watch web extension.
Home-page: https://github.com/an-otter-world/cow
Author: An Otter World
Author-email: an-otter-world@ki-dour.org
License: WTFPL
Keywords: Web Extension,Live Reload,firefox
Classifier: Development Status :: 2 - Pre-Alpha
Classifier: Intended Audience :: Developers
Classifier: Operating System :: OS Independent
Classifier: Programming Language :: Python
Classifier: Programming Language :: Python :: 3.8
License-File: LICENSE
Requires-Dist: watchdog
Requires-Dist: click
